[
    {
        "Path": "create-client-certificate-operation.markdown",
        "Name": "CreateClientCertificateOperation",
        "Mappings": []
    },
    {
        "Path": "get-certificate-operation.markdown",
        "Name": "GetCertificateOperation",
        "Mappings": []
    },
    {
        "Path": "get-certificates-operation.markdown",
        "Name": "GetCertificatesOperation",
        "Mappings": []
    },
    {
        "Path": "delete-certificate-operation.markdown",
        "Name": "DeleteCertificateOperation",
        "Mappings": []
    },
    {
        "Path": "put-client-certificate-operation.markdown",
        "Name": "PutClientCertificateOperation",
        "Mappings": []
    },
    {
        "Path": "get-serverwide-client-configuration-operation.markdown",
        "Name": "GetServerWideClientConfigurationOperation",
        "Mappings": []
    },
    {
        "Path": "put-serverwide-client-configuration-operation.markdown",
        "Name": "PutServerWideClientConfigurationOperation",
        "Mappings": []
    },

    {
        "Path": "reset-etl-operation.markdown",
        "Name": "ResetEtlOperation",
        "Mappings": []
    },

    {
        "Path": "add-database-node-operation.markdown",
        "Name": "AddDatabaseNodeOperation",
        "Mappings": []
    },

    {
        "Path": "compact-database-operation.markdown",
        "Name": "CompactDatabaseOperation",
        "Mappings": [
            {
                "Version": 3.5,
                "Key": "client-api/commands/admin/compaction"
            }
        ]
    },
    {
        "Path": "create-database-operation.markdown",
        "Name": "CreateDatabaseOperation",
        "Mappings": []
    },
    {
        "Path": "delete-database-operation.markdown",
        "Name": "DeleteDatabasesOperation",
        "Mappings": []
    },
    {
        "Path": "get-build-number-operation.markdown",
        "Name": "GetBuildNumberOperation",
        "Mappings": []
    },

    {
        "Path": "get-database-names-operation.markdown",
        "Name": "GetDatabaseNamesOperation",
        "Mappings": [
            {
                "Version": 3.5,
                "Key": "client-api/commands/how-to/get-names-of-all-databases-on-a-server"
            }
        ]
    },

    {
        "Path": "get-database-topology-operation.markdown",
        "Name": "GetDatabaseTopology",
        "Mappings": []
    },

    {
        "Path": "get-serverwide-operation-state-operation.markdown",
        "Name": "GetServerWideOperationStateOperation",
        "Mappings": []
    },

    {
        "Path": "modify-conflict-solver-operation.markdown",
        "Name": "ModifyConflictSolverOperation",
        "Mappings": []
    },

    {
        "Path": "promote-database-node-operation.markdown",
        "Name": "PromoteDatabaseNodeOperation",
        "Mappings": []
    },
    {
        "Path": "restore-backup-operation.markdown",
        "Name": "RestoreBackupOperation",
        "Mappings": []
    },
    {
        "Path": "start-backup-operation.markdown",
        "Name": "StartBackupOperation",
        "Mappings": []
    },
    {
        "Path": "toggle-databases-state-operation.markdown",
        "Name": "ToggleDatabasesStateOperation",
        "Mappings": []
    }
]
