[
    {
        "Path": "databases-list-view.markdown",
        "Name": "List View",
        "DiscussionId": "6ed47a0a-2068-49cf-9e4e-f9b6f6b4fc8e",
        "LastSupportedVersion": "5.1",
        "Mappings": [
            {
                "Version": 5.2,
                "Key": "studio/database/databases-list-view"
            }
        ]
    },
    {
        "Path": "/create-new-database",
        "Name": "Create New Database",
        "LastSupportedVersion": "5.1",
        "Mappings": [
            {
                "Version": 5.2,
                "Key": "studio/database/create-new-database"
            }
        ]
    }
]
